microdata/__init__.py
microdata/plugin.py
microdata/tests.py
microdata/test-resources/microdata_itemprop.rst
microdata/test-resources/microdata_itemprop_url.rst
microdata/test-resources/microdata_itemscope.rst
microdata/test-resources/microdata_itemscope_nested.rst
microdata/test-resources/microdata_itemscope_nested_compact.rst
microdata/test-resources/microdata_itemscope_tag.rst
pelican_microdata-0.3.0.dist-info/DESCRIPTION.rst
pelican_microdata-0.3.0.dist-info/METADATA
pelican_microdata-0.3.0.dist-info/RECORD
pelican_microdata-0.3.0.dist-info/WHEEL
pelican_microdata-0.3.0.dist-info/metadata.json
pelican_microdata-0.3.0.dist-info/top_level.txt
