Metadata-Version: 2.0
Name: pelican-microdata
Version: 0.3.0
Summary: Microdata semantic markups support for Pelican Blog Generator
Home-page: https://github.com/noirbizarre/pelican-microdata
Author: Axel Haustant
Author-email: noirbizarre+pelican@gmail.com
License: LGPL
Platform: UNKNOWN
Classifier: Development Status :: 4 - Beta
Classifier: Programming Language :: Python
Classifier: Environment :: Web Environment
Classifier: Operating System :: OS Independent
Classifier: Intended Audience :: Developers
Classifier: Topic :: System :: Software Distribution
Classifier: Programming Language :: Python
Classifier: Programming Language :: Python :: 2.7
Classifier: Programming Language :: Python :: 3
Classifier: Programming Language :: Python :: 3.3
Classifier: Programming Language :: Python :: 3.4
Classifier: Programming Language :: Python :: 3.5
Classifier: Programming Language :: Python :: 3.6
Classifier: Topic :: Software Development :: Libraries :: Python Modules
Classifier: License :: OSI Approved :: GNU Library or Lesser General Public License (LGPL)
Requires-Dist: pelican (>=3.7.0)
Provides-Extra: test
Requires-Dist: lxml; extra == 'test'
